[
  {
    "asset": "LIG1",
    "total_percent": 18.029709712244223,
    "avg_daily_percent": 0.09586452416319169
  },
  {
    "asset": "Bitcoin",
    "total_percent": -30.32350072207145,
    "avg_daily_percent": -0.19200006843345108
  },
  {
    "asset": "Ethereum",
    "total_percent": -41.6780792785178,
    "avg_daily_percent": -0.2863934521538214
  },
  {
    "asset": "S&P 500",
    "total_percent": 7.730255242683892,
    "avg_daily_percent": 0.05864733271427891
  },
  {
    "asset": "Alphabet",
    "total_percent": 5.88485255385891,
    "avg_daily_percent": 0.04503535126785252
  },
  {
    "asset": "Gold",
    "total_percent": -11.742651385121894,
    "avg_daily_percent": -0.09830851416208208
  }
]