[
  {
    "asset": "LIG1",
    "total_percent": 13.201621047163714,
    "avg_daily_percent": 0.16547048474917503
  },
  {
    "asset": "Bitcoin",
    "total_percent": -28.34574117243185,
    "avg_daily_percent": -0.40078217872138167
  },
  {
    "asset": "Ethereum",
    "total_percent": -37.178846947652936,
    "avg_daily_percent": -0.558528777884082
  },
  {
    "asset": "S&P 500",
    "total_percent": -4.7288072867782915,
    "avg_daily_percent": -0.08966847942388778
  },
  {
    "asset": "Alphabet",
    "total_percent": -9.093942353219697,
    "avg_daily_percent": -0.176406343458535
  },
  {
    "asset": "Gold",
    "total_percent": 1.9854437188379315,
    "avg_daily_percent": 0.03575167752301045
  }
]