[
  {
    "asset": "LIG1",
    "total_percent": 4.371016673614947,
    "avg_daily_percent": 0.12590811794308543
  },
  {
    "asset": "Bitcoin",
    "total_percent": -30.607342345954336,
    "avg_daily_percent": -1.0098363461180648
  },
  {
    "asset": "Ethereum",
    "total_percent": -41.662944664614045,
    "avg_daily_percent": -1.4858854049827008
  },
  {
    "asset": "S&P 500",
    "total_percent": -0.8458159140063315,
    "avg_daily_percent": -0.038602239946927686
  },
  {
    "asset": "Alphabet",
    "total_percent": -8.081822250828596,
    "avg_daily_percent": -0.38231900621215065
  },
  {
    "asset": "Gold",
    "total_percent": 9.005322206145049,
    "avg_daily_percent": 0.3756015457523132
  }
]